django_lookups/__init__.py
django_lookups/models.py
django_lookups/utils.py
django_lookups-0.1.3.dist-info/LICENSE
django_lookups-0.1.3.dist-info/WHEEL
django_lookups-0.1.3.dist-info/METADATA
django_lookups-0.1.3.dist-info/RECORD
