Metadata-Version: 2.1
Name: django-lookups
Version: 0.1.3
Summary: 
Home-page: https://github.com/mistahchris/django_lookups
License: Unlicense
Keywords: django,lookup table,model
Author: mistahchris
Author-email: chris@thesogu.com
Requires-Python: >=3.6,<4.0
Classifier: License :: OSI Approved :: The Unlicense (Unlicense)
Classifier: License :: Other/Proprietary License
Classifier: Programming Language :: Python :: 3
Classifier: Programming Language :: Python :: 3.6
Classifier: Programming Language :: Python :: 3.7
Classifier: Programming Language :: Python :: 3.8
Classifier: Programming Language :: Python :: 3.9
Classifier: Topic :: Software Development :: Libraries :: Python Modules
Requires-Dist: Django (>=1.11,<4)
Project-URL: Repository, https://github.com/mistahchris/django_lookups
